Metadata-Version: 2.1
Name: rsxtr
Version: 0.0.1
Summary: Platformlar arası uygulamalar için tasarlanan, yorumlanan, statik olarak yazılan çoklu paradigmalı genel amaçlı bir programlama dili olan R#'ın Türkçe versiyonu.
Home-page: https://github.com/Aermoss/RSX-TR
Author: Yusuf Rencber
Author-email: yusufrencber546@gmail.com
License: MIT
Platform: UNKNOWN
License-File: LICENSE
